qtoggleserver/paradox/__init__.py
qtoggleserver/paradox/area.py
qtoggleserver/paradox/constants.py
qtoggleserver/paradox/exceptions.py
qtoggleserver/paradox/output.py
qtoggleserver/paradox/paradoxalarm.py
qtoggleserver/paradox/paradoxport.py
qtoggleserver/paradox/remote.py
qtoggleserver/paradox/system.py
qtoggleserver/paradox/typing.py
qtoggleserver/paradox/zone.py
qtoggleserver_paradox-1.8.1.dist-info/licenses/LICENSE.txt
qtoggleserver_paradox-1.8.1.dist-info/METADATA
qtoggleserver_paradox-1.8.1.dist-info/WHEEL
qtoggleserver_paradox-1.8.1.dist-info/top_level.txt
qtoggleserver_paradox-1.8.1.dist-info/RECORD
