Metadata-Version: 2.4
Name: qtoggleserver-paradox
Version: 1.8.1
Summary: Control your Paradox alarm with qToggleServer
Author-email: Calin Crisan <ccrisan@gmail.com>
License: Apache 2.0
Requires-Python: >=3.11
License-File: LICENSE.txt
Requires-Dist: paradox-alarm-interface<4,>=3
Requires-Dist: pyserial
Requires-Dist: pyserial-asyncio
Requires-Dist: requests
Dynamic: license-file
